cloud_downloader/__init__.py
cloud_downloader/cloud_downloader.py
cloud_downloader/utils.py
cloud_downloader_equitania-0.0.4.dist-info/LICENSE.txt
cloud_downloader_equitania-0.0.4.dist-info/METADATA
cloud_downloader_equitania-0.0.4.dist-info/WHEEL
cloud_downloader_equitania-0.0.4.dist-info/entry_points.txt
cloud_downloader_equitania-0.0.4.dist-info/top_level.txt
cloud_downloader_equitania-0.0.4.dist-info/RECORD
