Metadata-Version: 2.1
Name: cloud-downloader-equitania
Version: 0.0.4
Summary: A package to download files from cloud services
Author: Equitania Software GmbH
Author-email: info@equitania.de
License: UNKNOWN
Platform: UNKNOWN
Classifier: Programming Language :: Python :: 3
Classifier: License :: OSI Approved :: GNU Affero General Public License v3
Classifier: Operating System :: OS Independent
Requires-Python: >=3.6
License-File: LICENSE.txt
Requires-Dist: click (>=8.1.3)
Requires-Dist: requests (>=2.22.0)
